pynqmetadata/__init__.py
pynqmetadata/version.txt
pynqmetadata/errors/__init__.py
pynqmetadata/errors/construction_errors.py
pynqmetadata/errors/dfx_errors.py
pynqmetadata/errors/metadata_type_errors.py
pynqmetadata/errors/misc_errors.py
pynqmetadata/errors/parsing_errors.py
pynqmetadata/errors/query_errors.py
pynqmetadata/errors/validation_errors.py
pynqmetadata/frontends/__init__.py
pynqmetadata/frontends/hwh_frontend.py
pynqmetadata/frontends/json_frontend.py
pynqmetadata/frontends/metadata.py
pynqmetadata/frontends/xsa_frontend.py
pynqmetadata/frontends/visualisations/__init__.py
pynqmetadata/frontends/visualisations/metadata_vis.py
pynqmetadata/frontends/visualisations/classic_edk_plot/__init__.py
pynqmetadata/frontends/visualisations/classic_edk_plot/classic_edk_plot.py
pynqmetadata/frontends/visualisations/conmatvis/__init__.py
pynqmetadata/frontends/visualisations/conmatvis/conmatvis.py
pynqmetadata/frontends/visualisations/lib/d3.v4.min.js
pynqmetadata/frontends/visualisations/lib/keytooltip.js
pynqmetadata/frontends/visualisations/lib/tooltip.js
pynqmetadata/models/__init__.py
pynqmetadata/models/addrmap.py
pynqmetadata/models/bit_field.py
pynqmetadata/models/block.py
pynqmetadata/models/bus_connection.py
pynqmetadata/models/clk_port.py
pynqmetadata/models/core.py
pynqmetadata/models/dfx_core.py
pynqmetadata/models/hierarchy.py
pynqmetadata/models/interrupt_signal.py
pynqmetadata/models/ip_core.py
pynqmetadata/models/manager_port.py
pynqmetadata/models/metadata_extension.py
pynqmetadata/models/metadata_object.py
pynqmetadata/models/microblaze_core.py
pynqmetadata/models/module.py
pynqmetadata/models/parameter.py
pynqmetadata/models/port.py
pynqmetadata/models/proc_sys_core.py
pynqmetadata/models/register.py
pynqmetadata/models/rst_port.py
pynqmetadata/models/scalar_port.py
pynqmetadata/models/signal.py
pynqmetadata/models/stream_port.py
pynqmetadata/models/subordinate_port.py
pynqmetadata/models/ultrascale_proc_sys_core.py
pynqmetadata/models/vlnv.py
pynqmetadata-0.1.2.dist-info/LICENSE
pynqmetadata-0.1.2.dist-info/METADATA
pynqmetadata-0.1.2.dist-info/WHEEL
pynqmetadata-0.1.2.dist-info/top_level.txt
pynqmetadata-0.1.2.dist-info/RECORD
