Metadata-Version: 2.1
Name: pynqmetadata
Version: 0.1.2
Summary: Extensible, Modular, Metadata layer for PYNQ projects
Home-page: http://github.com/Xilinx/PYNQ-Metadata
Author: Pynq
Author-email: pynq_support@xilinx.com
License: BSD 3-Clause
Platform: UNKNOWN
Requires-Python: >=3.5.2
Requires-Dist: jsonschema (>=3.2.0)
Requires-Dist: pydantic
